{
  "kind": "collectionType",
  "collectionName": "sponsors",
  "info": {
    "name": "Sponsor"
  },
  "options": {
    "increments": true,
    "timestamps": true,
    "draftAndPublish": true
  },
  "pluginOptions": {},
  "attributes": {
    "name": {
      "type": "string"
    },
    "link": {
      "type": "string"
    },
    "logo": {
      "model": "file",
      "via": "related",
      "allowedTypes": [
        "images"
      ],
      "plugin": "upload",
      "required": false,
      "pluginOptions": {}
    }
  }
}
